<?xml version="1.0" encoding="utf-8"?>
<django-objects version="1.0">
  <object model="portfolio.post" pk="1">
    <field name="title" type="CharField">YO WAddup</field>
    <field name="slug" type="SlugField">HUNTS_HUNTS</field>
    <field name="author" rel="ManyToOneRel" to="auth.user">1</field>
    <field name="body" type="TextField">A POST FROM THE ADMIN /EDIT/</field>
    <field name="date_added" type="DateTimeField">2022-05-25T08:29:40.873717+00:00</field>
  </object>
  <object model="portfolio.post" pk="2">
    <field name="title" type="CharField">I bet on luna</field>
    <field name="slug" type="SlugField">Crypto_Scam</field>
    <field name="author" rel="ManyToOneRel" to="auth.user">1</field>
    <field name="body" type="TextField">LET'S GOOOO</field>
    <field name="date_added" type="DateTimeField">2022-05-25T09:23:33.559825+00:00</field>
  </object>
  <object model="portfolio.comment" pk="2">
    <field name="post" rel="ManyToOneRel" to="portfolio.post">1</field>
    <field name="name" type="CharField">yooyoy</field>
    <field name="email" type="CharField">fsdves@gmail.com</field>
    <field name="body" type="TextField">fdhmgobimxdlvçc</field>
    <field name="date_added" type="DateTimeField">2022-05-25T08:53:25.365161+00:00</field>
  </object>
  <object model="portfolio.comment" pk="3">
    <field name="post" rel="ManyToOneRel" to="portfolio.post">1</field>
    <field name="name" type="CharField">yooyoy</field>
    <field name="email" type="CharField">fsdves@gmail.com</field>
    <field name="body" type="TextField">b nhvbmhbj</field>
    <field name="date_added" type="DateTimeField">2022-05-25T08:53:34.492318+00:00</field>
  </object>
  <object model="portfolio.comment" pk="4">
    <field name="post" rel="ManyToOneRel" to="portfolio.post">1</field>
    <field name="name" type="CharField">yooyoy</field>
    <field name="email" type="CharField">fsdves@gmail.com</field>
    <field name="body" type="TextField">nbjmhumhu</field>
    <field name="date_added" type="DateTimeField">2022-05-25T08:54:31.270899+00:00</field>
  </object>
  <object model="portfolio.comment" pk="5">
    <field name="post" rel="ManyToOneRel" to="portfolio.post">1</field>
    <field name="name" type="CharField">yooyoy</field>
    <field name="email" type="CharField">fsdves@gmail.com</field>
    <field name="body" type="TextField">nbjmhumhu</field>
    <field name="date_added" type="DateTimeField">2022-05-25T08:54:50.030430+00:00</field>
  </object>
  <object model="portfolio.comment" pk="6">
    <field name="post" rel="ManyToOneRel" to="portfolio.post">1</field>
    <field name="name" type="CharField">yooyoy</field>
    <field name="email" type="CharField">REFAS@fmdajmcd.com</field>
    <field name="body" type="TextField">njkhjhuuiiu,ui</field>
    <field name="date_added" type="DateTimeField">2022-05-25T08:54:55.556022+00:00</field>
  </object>
  <object model="portfolio.comment" pk="7">
    <field name="post" rel="ManyToOneRel" to="portfolio.post">1</field>
    <field name="name" type="CharField">yooyoy</field>
    <field name="email" type="CharField">fsdves@gmail.com</field>
    <field name="body" type="TextField">jnkm</field>
    <field name="date_added" type="DateTimeField">2022-05-25T08:55:38.081412+00:00</field>
  </object>
  <object model="portfolio.comment" pk="8">
    <field name="post" rel="ManyToOneRel" to="portfolio.post">2</field>
    <field name="name" type="CharField">gragr</field>
    <field name="email" type="CharField">REFAS@fmdajmcd.com</field>
    <field name="body" type="TextField">LETS GOOO UP ON LUNA</field>
    <field name="date_added" type="DateTimeField">2022-05-25T09:24:02.265694+00:00</field>
  </object>
  <object model="portfolio.comment" pk="9">
    <field name="post" rel="ManyToOneRel" to="portfolio.post">2</field>
    <field name="name" type="CharField">yooyoy</field>
    <field name="email" type="CharField">REFAS@fmdajmcd.com</field>
    <field name="body" type="TextField">PFEALPV*LDACSPCAPSCAPs+</field>
    <field name="date_added" type="DateTimeField">2022-05-25T09:41:17.431011+00:00</field>
  </object>
  <object model="portfolio.comment" pk="10">
    <field name="post" rel="ManyToOneRel" to="portfolio.post">2</field>
    <field name="name" type="CharField">gragr</field>
    <field name="email" type="CharField">fsdves@gmail.comhumio</field>
    <field name="body" type="TextField">iuhiujil,ol</field>
    <field name="date_added" type="DateTimeField">2022-05-25T09:41:41.064410+00:00</field>
  </object>
  <object model="portfolio.comment" pk="11">
    <field name="post" rel="ManyToOneRel" to="portfolio.post">2</field>
    <field name="name" type="CharField">hrt</field>
    <field name="email" type="CharField">fh@alfcsa.com</field>
    <field name="body" type="TextField">FGAwefaw</field>
    <field name="date_added" type="DateTimeField">2022-05-25T17:51:31.612360+00:00</field>
  </object>
</django-objects>